chart_tools/__init__.py
chart_tools/utils.py
chart_tools/data/__init__.py
chart_tools/data/datasource.py
chart_tools/data/dfcache.py
chart_tools/data/library.py
chart_tools/data/source.py
chart_tools/heatmaps/__init__.py
chart_tools/heatmaps/superheat.py
chart_tools-0.1.3.dist-info/METADATA
chart_tools-0.1.3.dist-info/WHEEL
chart_tools-0.1.3.dist-info/licenses/LICENSE
chart_tools-0.1.3.dist-info/RECORD
