Metadata-Version: 2.1
Name: chart-tools
Version: 0.1.3
Summary: Powerful visualizations, and an easy to use, interactive api for exploring and loading datasets
Project-URL: Documentation, https://github.com/ryayoung/chart-tools
Author-email: Ryan Young <dev@ryayoung.com>
Maintainer-email: Ryan Young <dev@ryayoung.com>
License: Copyright 2022 Ryan Young
License-File: LICENSE
Keywords: chart,graph,visualization
Classifier: License :: OSI Approved :: MIT License
Classifier: Operating System :: OS Independent
Classifier: Programming Language :: Python :: 3.9
Requires-Python: >=3.9
Requires-Dist: matplotlib
Requires-Dist: numpy
Requires-Dist: pandas
Requires-Dist: requests
Requires-Dist: seaborn
